aritech_client/__init__.py
aritech_client/cli.py
aritech_client/client.py
aritech_client/errors.py
aritech_client/event_parser.py
aritech_client/event_types.py
aritech_client/message_helpers.py
aritech_client/messages.py
aritech_client/monitor.py
aritech_client/protocol.py
aritech_client/py.typed
aritech_client/state.py
aritech_client/.claude/settings.local.json
aritech_client-0.5.1.dist-info/METADATA
aritech_client-0.5.1.dist-info/WHEEL
aritech_client-0.5.1.dist-info/entry_points.txt
aritech_client-0.5.1.dist-info/licenses/LICENSE
aritech_client-0.5.1.dist-info/RECORD
