Metadata-Version: 2.4
Name: aritech-client
Version: 0.5.1
Summary: Unofficial Python client library for ATS alarm panels
Project-URL: Homepage, https://github.com/sebakerckhof/atsadvisor
Project-URL: Repository, https://github.com/sebakerckhof/atsadvisor
Author: Seba Kerckhof
License-Expression: MIT
License-File: LICENSE
Keywords: alarm,aritech,ats,carrier,home-automation,security
Classifier: Development Status :: 3 - Alpha
Classifier: Framework :: AsyncIO
Classifier: Intended Audience :: Developers
Classifier: License :: OSI Approved :: MIT License
Classifier: Operating System :: OS Independent
Classifier: Programming Language :: Python :: 3
Classifier: Programming Language :: Python :: 3.11
Classifier: Programming Language :: Python :: 3.12
Classifier: Programming Language :: Python :: 3.13
Classifier: Topic :: Home Automation
Classifier: Topic :: Security
Classifier: Typing :: Typed
Requires-Python: >=3.11
Requires-Dist: pycryptodome>=3.19.0
Provides-Extra: dev
Requires-Dist: mypy>=1.11.0; extra == 'dev'
Requires-Dist: pytest-asyncio>=0.24.0; extra == 'dev'
Requires-Dist: pytest>=8.0.0; extra == 'dev'
Requires-Dist: ruff>=0.7.0; extra == 'dev'
